<annotation>
	<folder>resized2</folder>
	<filename>Givrage2_069.jpg</filename>
	<path>C:\workspaces\models\research\object_detection\test_image-enregistre\resized2\Givrage2_069.jpg</path>
	<source>
		<database>Unknown</database>
	</source>
	<size>
		<width>1028</width>
		<height>772</height>
		<depth>3</depth>
	</size>
	<segmented>0</segmented>
	<object>
		<name>Givrage</name>
		<pose>Unspecified</pose>
		<truncated>0</truncated>
		<difficult>0</difficult>
		<bndbox>
			<xmin>609</xmin>
			<ymin>366</ymin>
			<xmax>674</xmax>
			<ymax>489</ymax>
		</bndbox>
	</object>
</annotation>
