<annotation>
	<folder>train</folder>
	<filename>Quashqai_017.jpg</filename>
	<path>C:\Users\Bruno\Documents\Github\object_detection_demo2\data\images\train\Quashqai_017.jpg</path>
	<source>
		<database>Unknown</database>
	</source>
	<size>
		<width>640</width>
		<height>480</height>
		<depth>3</depth>
	</size>
	<segmented>0</segmented>
	<object>
		<name>Quashquai</name>
		<pose>Unspecified</pose>
		<truncated>0</truncated>
		<difficult>0</difficult>
		<bndbox>
			<xmin>309</xmin>
			<ymin>87</ymin>
			<xmax>622</xmax>
			<ymax>362</ymax>
		</bndbox>
	</object>
</annotation>
